extratools_git/__init__.py
extratools_git/prompt.py
extratools_git/repo.py
extratools_git/status.py
extratools_git-0.1.3.dist-info/METADATA
extratools_git-0.1.3.dist-info/WHEEL
extratools_git-0.1.3.dist-info/entry_points.txt
extratools_git-0.1.3.dist-info/licenses/LICENSE
extratools_git-0.1.3.dist-info/RECORD
